{
  "id": "8f1c11ab-f81f-4ec7-9178-187c55ce10dd",
  "name": "[NEW] 비페스타 곤약볼 클렌징폼 브라이트닝 120g",
  "price": "6900",
  "brand": "비페스타",
  "category": "4",
  "site": 1,
  "site_id": "A000000152602",
  "site_category": "1000001001000010001",
  "link": "https://www.oliveyoung.co.kr/store/goods/getGoodsDetail.do?goodsNo=A000000152602&dispCatNo=1000001001000010001&trackingCd&curation&egcode&rccode&egrankcode",
  "image_url": "https://image.oliveyoung.co.kr/uploads/images/goods/400/10/0000/0015/A00000015260202ko.jpg?l=ko",
  "volume": "120g",
  "expiration_date": "제조일로부터 3년",
  "usage": "젖은 손바닥에 적량(2~3cm)를 덜어 미지근한 물로 충분히 거품을 낸 뒤 거품을 얼굴 전체에 펴서 세안한 후 미온수로 잘 씻어냅니다.*눈에 들어가지 않도록 주의하고, 들어갔을 때에는 즉시 씻어냅니다.",
  "origin": "일본",
  "ingredients": "정제수, 다이프로필렌글라이콜, 폴리글리세릴-10라우레이트, 폴리글리세릴-3카프릴레이트, 피이지-6카프릴릭/카프릭글리세라이즈, 피이지-400, 피피지-14폴리글리세릴-2에터, 페녹시에탄올, 소듐시트레이트, 글리세린, 소듐미리스토일글루타메이트, 다이소듐이디티에이, 시트릭애씨드, 다이소듐아스코빌설페이트, 풀루란, 락틱애씨드, 피씨에이에틸코코일알지네이트, 하이드롤라이즈드하이알루로닉애씨드",
  "caution": "1) 화장품 사용 시 또는 사용 후 직사광선에 의하여 사용부위가 붉은 반점, 부어오름 또는 가려움증 등의 이상 증상이나 부작용이 있는 경우 전문의 등과 상담할 것2) 상처가 있는 부위 등에는 사용을 자제할 것3) 보관 및 취급시의 주의사항(가) 어린이의 손이 닿지 않는 곳에 보관할 것(나) 직사광선을 피해서 보관할 것4) 눈에 들어갔을 때 즉시 씻어 낼 것"
}